hhpy/.DS_Store
hhpy/__init__.py
hhpy/__init__.pyc
hhpy/__version__.py
hhpy/ds.py
hhpy/entry_points.py
hhpy/ipython.py
hhpy/main.py
hhpy/modelling.py
hhpy/plotting.py
hhpy/regression.py
hhpy-0.3.1.dist-info/LICENSE.txt
hhpy-0.3.1.dist-info/METADATA
hhpy-0.3.1.dist-info/WHEEL
hhpy-0.3.1.dist-info/entry_points.txt
hhpy-0.3.1.dist-info/top_level.txt
hhpy-0.3.1.dist-info/RECORD
