Metadata-Version: 2.1
Name: hhpy
Version: 0.3.1
Summary: Convenient Data Science
Home-page: https://github.com/rhedak/hhpy
Author: Henrik Hanssen
Author-email: Henrik Hanssen <rhedak00@yahoo.de>
License: Apache 2.0
Project-URL: Homepage, https://github.com/rhedak/hhpy
Keywords: package development template
Classifier: Programming Language :: Python :: 3
Classifier: License :: OSI Approved :: MIT License
Classifier: Operating System :: OS Independent
Requires-Python: >=3.8
License-File: LICENSE.txt
Requires-Dist: numpy
Requires-Dist: pandas
Requires-Dist: scipy
Requires-Dist: matplotlib
Requires-Dist: scikit-learn
Requires-Dist: seaborn
Requires-Dist: colour
Requires-Dist: pytest
Requires-Dist: requests
Requires-Dist: IPython
Requires-Dist: docrep
Requires-Dist: h5py
Requires-Dist: openpyxl
Requires-Dist: xlrd
